pre_commit_matlab/__init__.py
pre_commit_matlab/matlab_reflow_comments.py
pre_commit_matlab-1.2.0.dist-info/entry_points.txt
pre_commit_matlab-1.2.0.dist-info/LICENSE
pre_commit_matlab-1.2.0.dist-info/WHEEL
pre_commit_matlab-1.2.0.dist-info/METADATA
pre_commit_matlab-1.2.0.dist-info/RECORD
